qucumber/__init__.py
qucumber/__version__.py
qucumber/callbacks/__init__.py
qucumber/callbacks/callback.py
qucumber/callbacks/callback_list.py
qucumber/callbacks/early_stopping.py
qucumber/callbacks/lambda_callback.py
qucumber/callbacks/liveplotting.py
qucumber/callbacks/logger.py
qucumber/callbacks/metric_evaluator.py
qucumber/callbacks/model_saver.py
qucumber/callbacks/observable_evaluator.py
qucumber/callbacks/timer.py
qucumber/callbacks/variance_based_early_stopping.py
qucumber/nn_states/__init__.py
qucumber/nn_states/complex_wavefunction.py
qucumber/nn_states/density_matrix.py
qucumber/nn_states/neural_state.py
qucumber/nn_states/positive_wavefunction.py
qucumber/nn_states/wavefunction.py
qucumber/observables/__init__.py
qucumber/observables/entanglement.py
qucumber/observables/interactions.py
qucumber/observables/observable.py
qucumber/observables/pauli.py
qucumber/observables/system.py
qucumber/observables/utils.py
qucumber/rbm/__init__.py
qucumber/rbm/binary_rbm.py
qucumber/rbm/purification_rbm.py
qucumber/utils/__init__.py
qucumber/utils/cplx.py
qucumber/utils/data.py
qucumber/utils/gradients_utils.py
qucumber/utils/training_statistics.py
qucumber/utils/unitaries.py
qucumber-1.3.3.dist-info/LICENSE
qucumber-1.3.3.dist-info/LICENSE_HEADER
qucumber-1.3.3.dist-info/METADATA
qucumber-1.3.3.dist-info/WHEEL
qucumber-1.3.3.dist-info/top_level.txt
qucumber-1.3.3.dist-info/RECORD
