Metadata-Version: 2.1
Name: qucumber
Version: 1.3.3
Summary: Neural Network Quantum State Tomography.
Home-page: http://github.com/PIQuIL/QuCumber
Author: PIQuIL
Author-email: piquildbeets@gmail.com
License: Apache License 2.0
Classifier: License :: OSI Approved :: Apache Software License
Classifier: Programming Language :: Python :: 3
Classifier: Programming Language :: Python :: 3.6
Classifier: Programming Language :: Python :: 3.7
Classifier: Programming Language :: Python :: 3.8
Classifier: Programming Language :: Python :: 3.9
Classifier: Programming Language :: Python :: 3.10
Classifier: Programming Language :: Python :: 3.11
Classifier: Programming Language :: Python :: Implementation :: CPython
Classifier: Operating System :: OS Independent
Classifier: Intended Audience :: Science/Research
Classifier: Topic :: Scientific/Engineering
Classifier: Topic :: Scientific/Engineering :: Artificial Intelligence
Classifier: Topic :: Scientific/Engineering :: Physics
Requires-Python: >=3.6.1,<4
License-File: LICENSE
License-File: LICENSE_HEADER
Requires-Dist: tqdm (>=4.23)
Requires-Dist: numpy (>=1.13)
Requires-Dist: scipy (>=1.3.3)
Requires-Dist: matplotlib (>=2.2)
Requires-Dist: torch (<2.1,>=1.2) ; sys_platform != "win32"
Provides-Extra: appveyor
Requires-Dist: setuptools (>=40.0.0) ; extra == 'appveyor'
Requires-Dist: wheel (>=0.31.1) ; extra == 'appveyor'
Requires-Dist: pytest (>=3.7.1) ; extra == 'appveyor'
Requires-Dist: tox (>=3.2.1) ; extra == 'appveyor'
Provides-Extra: coverage
Requires-Dist: pytest (>=3.7.1) ; extra == 'coverage'
Requires-Dist: tox (>=3.2.1) ; extra == 'coverage'
Requires-Dist: pytest-cov (>=2.5.1) ; extra == 'coverage'
Provides-Extra: dev
Requires-Dist: setuptools (>=40.0.0) ; extra == 'dev'
Requires-Dist: wheel (>=0.31.1) ; extra == 'dev'
Requires-Dist: pytest (>=3.7.1) ; extra == 'dev'
Requires-Dist: tox (>=3.2.1) ; extra == 'dev'
Requires-Dist: pytest-cov (>=2.5.1) ; extra == 'dev'
Requires-Dist: radon[flake8] (>=4.3.2) ; extra == 'dev'
Requires-Dist: flake8 (>=3.7.9) ; extra == 'dev'
Requires-Dist: flake8-bugbear (>=19.3.0) ; extra == 'dev'
Requires-Dist: flake8-fixme (>=1.1.1) ; extra == 'dev'
Requires-Dist: invoke (>=1.1.1) ; extra == 'dev'
Requires-Dist: nbconvert (<6.0,>=5.3.1) ; extra == 'dev'
Requires-Dist: sphinx-rtd-theme (>=0.4.1) ; extra == 'dev'
Requires-Dist: sphinx-autobuild (>=0.7.1) ; extra == 'dev'
Requires-Dist: pre-commit (>=1.10.5) ; extra == 'dev'
Requires-Dist: nbval (>=0.9.1) ; extra == 'dev'
Requires-Dist: bump2version (>=1.0.0) ; extra == 'dev'
Requires-Dist: black (==19.3b0) ; (python_version >= "3.6") and extra == 'dev'
Provides-Extra: docs
Requires-Dist: sphinx-rtd-theme (>=0.4.1) ; extra == 'docs'
Requires-Dist: sphinx-autobuild (>=0.7.1) ; extra == 'docs'
Provides-Extra: rtd
Provides-Extra: style
Requires-Dist: radon[flake8] (>=4.3.2) ; extra == 'style'
Requires-Dist: flake8 (>=3.7.9) ; extra == 'style'
Requires-Dist: flake8-bugbear (>=19.3.0) ; extra == 'style'
Requires-Dist: flake8-fixme (>=1.1.1) ; extra == 'style'
Requires-Dist: invoke (>=1.1.1) ; extra == 'style'
Requires-Dist: nbconvert (<6.0,>=5.3.1) ; extra == 'style'
Requires-Dist: black (==19.3b0) ; (python_version >= "3.6") and extra == 'style'
Provides-Extra: test
Requires-Dist: pytest (>=3.7.1) ; extra == 'test'
Requires-Dist: tox (>=3.2.1) ; extra == 'test'
Provides-Extra: travis
Requires-Dist: setuptools (>=40.0.0) ; extra == 'travis'
Requires-Dist: wheel (>=0.31.1) ; extra == 'travis'
Requires-Dist: pytest (>=3.7.1) ; extra == 'travis'
Requires-Dist: tox (>=3.2.1) ; extra == 'travis'
Requires-Dist: pytest-cov (>=2.5.1) ; extra == 'travis'
Requires-Dist: radon[flake8] (>=4.3.2) ; extra == 'travis'
Requires-Dist: flake8 (>=3.7.9) ; extra == 'travis'
Requires-Dist: flake8-bugbear (>=19.3.0) ; extra == 'travis'
Requires-Dist: flake8-fixme (>=1.1.1) ; extra == 'travis'
Requires-Dist: invoke (>=1.1.1) ; extra == 'travis'
Requires-Dist: nbconvert (<6.0,>=5.3.1) ; extra == 'travis'
Requires-Dist: black (==19.3b0) ; (python_version >= "3.6") and extra == 'travis'
